cloudbypass/__init__.py
cloudbypass/__version__.py
cloudbypass/adapters.py
cloudbypass/api.py
cloudbypass/exceptions.py
cloudbypass/proxy.py
cloudbypass/sessions.py
cloudbypass-0.2.4.dist-info/METADATA
cloudbypass-0.2.4.dist-info/WHEEL
cloudbypass-0.2.4.dist-info/top_level.txt
cloudbypass-0.2.4.dist-info/RECORD
