Metadata-Version: 2.1
Name: cloudbypass
Version: 0.2.4
Summary: Cloudbypass SDK for Python.
Author: NULL
Author-email: python@cloudbypass.com
Keywords: cloudflare,bypass,turnstile,scraping,cloudbypass,scrapingbypass,waf,captcha,cloudflare-bypass,cloudflare-scraping
Classifier: License :: OSI Approved :: MIT License
Classifier: Programming Language :: Python
Classifier: Programming Language :: Python :: 3.7
Classifier: Programming Language :: Python :: 3.8
Classifier: Programming Language :: Python :: 3.9
Classifier: Programming Language :: Python :: 3.10
Classifier: Programming Language :: Python :: 3.11
Requires-Python: >=3.7
Requires-Dist: requests >=2.28.0
Requires-Dist: aiohttp >=3.8.6
